padawan/__init__.py
padawan/collated_dataset.py
padawan/concatenated_dataset.py
padawan/dataset.py
padawan/in_memory_dataset.py
padawan/joined_dataset.py
padawan/json_io.py
padawan/mapped_dataset.py
padawan/metadata.py
padawan/ordering.py
padawan/parallelize.py
padawan/persisted_dataset.py
padawan/progress.py
padawan/reindexed_dataset.py
padawan/renamed_dataset.py
padawan/repartitioned_dataset.py
padawan/sliced_dataset.py
padawan/write_metadata.py
padawan-0.14.dist-info/METADATA
padawan-0.14.dist-info/WHEEL
padawan-0.14.dist-info/licenses/LICENSE
padawan-0.14.dist-info/RECORD
