Metadata-Version: 2.4
Name: padawan
Version: 0.14
Summary: Wrangle partitioned data with polars.
Project-URL: Homepage, https://github.com/mwiebusch78/padawan
Project-URL: Bug Tracker, https://github.com/mwiebusch78/padawan/issues
Project-URL: Documentation, https://padawan.readthedocs.io/en/latest/
Author: Martin Wiebusch
License-File: LICENSE
Classifier: License :: OSI Approved :: MIT License
Classifier: Operating System :: OS Independent
Classifier: Programming Language :: Python :: 3
Requires-Python: >=3.7
Requires-Dist: cloudpickle
Requires-Dist: polars>=1.14.0
Requires-Dist: pyarrow
